{"id":"21047","name":"Projeto de Lei nº 43 de 2013","ementa":"Altera os dispositivos que menciona da Lei Municipal nº 2.247/2010, de 29/12/2010, que Institui o Plano de Classificação de Cargos e Funções para os Servidores da COMUSA - Serviços de Água e Esgoto de Novo Hamburgo, e dá outras providências.","bill_text_link":"https://sapl.camaranh.rs.gov.br/media/sapl/public/materialegislativa/2013/21047/21047_texto_integral.pdf","date":"12/04/2013","authors":["Executivo"],"status":[{"date":"20/05/2013","unidade_local":"Poder Executivo Municipal - EXEC","unidade_destine":"Arquivo - ARQUIVO","status":"Lei sancionada pelo(a) chefe do Executivo"},{"date":"17/05/2013","unidade_local":"Secretaria - SECRET","unidade_destine":"Poder Executivo Municipal - EXEC","status":"Autógrafo"},{"date":"16/05/2013","unidade_local":"Plenário - PLEN","unidade_destine":"Secretaria - SECRET","status":"Aprovado(a) em 2ª votação"},{"date":"14/05/2013","unidade_local":"Plenário - PLEN","unidade_destine":"Plenário - PLEN","status":"Aprovado(a) em 1ª votação"},{"date":"07/05/2013","unidade_local":"Coordenadoria Legislativa - COOLEG","unidade_destine":"Plenário - PLEN","status":"Incluído(a) na Ordem do Dia"},{"date":"02/05/2013","unidade_local":"COJUR - Comissão de Constituição, Justiça e Redação","unidade_destine":"Coordenadoria Legislativa - COOLEG","status":"Parecer favorável"},{"date":"25/04/2013","unidade_local":"COOSP - Comissão de Obras, Serviços Públicos e Mobilidade Urbana","unidade_destine":"COJUR - Comissão de Constituição, Justiça e Redação","status":"Parecer favorável"},{"date":"22/04/2013","unidade_local":"COFIN - Com.de Compet., Finanças, Orçamento, Economia e Planejamento","unidade_destine":"COJUR - Comissão de Constituição, Justiça e Redação","status":"Parecer favorável"},{"date":"17/04/2013","unidade_local":"Coordenadoria Legislativa - COOLEG","unidade_destine":"COJUR - Comissão de Constituição, Justiça e Redação","status":"Permanência em tramitação"},{"date":"16/04/2013","unidade_local":"Plenário - PLEN","unidade_destine":"Coordenadoria Legislativa - COOLEG","status":"Matéria lida no Expediente"}]}