{"id":"23287","name":"Projeto de Lei nº 142 de 2013","ementa":"Suprime o § 3º do art. 6º da Lei Municipal nº 43/75, de 31 de outubro de 1975, e dá nova redação ao § 4º do art. 5º, acrescentado pela Lei Municipal nº 1.967/2009, de 25 de março de 2009.","bill_text_link":"https://sapl.camaranh.rs.gov.br/media/sapl/public/materialegislativa/2013/23287/23287_texto_integral.odt","date":"13/09/2013","authors":["Mesa da Câmara Municipal"],"status":[{"date":"10/10/2013","unidade_local":"Poder Executivo Municipal - EXEC","unidade_destine":"Arquivo - ARQUIVO","status":"Lei sancionada pelo(a) chefe do Executivo"},{"date":"10/10/2013","unidade_local":"Secretaria - SECRET","unidade_destine":"Poder Executivo Municipal - EXEC","status":"Autógrafo"},{"date":"10/10/2013","unidade_local":"Plenário - PLEN","unidade_destine":"Secretaria - SECRET","status":"Aprovado(a) em 2ª votação"},{"date":"08/10/2013","unidade_local":"Plenário - PLEN","unidade_destine":"Plenário - PLEN","status":"Aprovado(a) em 1ª votação"},{"date":"03/10/2013","unidade_local":"Coordenadoria Legislativa - COOLEG","unidade_destine":"Plenário - PLEN","status":"Incluído(a) na Ordem do Dia"},{"date":"25/09/2013","unidade_local":"CODIR - Com. de Direitos Humanos, Cidadania e Defesa do Consumidor","unidade_destine":"Coordenadoria Legislativa - COOLEG","status":"Parecer favorável"},{"date":"24/09/2013","unidade_local":"COJUR - Comissão de Constituição, Justiça e Redação","unidade_destine":"CODIR - Com. de Direitos Humanos, Cidadania e Defesa do Consumidor","status":"Parecer de constitucionalidade"},{"date":"18/09/2013","unidade_local":"Assessoria de Comissões Permanentes - ASCOPE","unidade_destine":"Assessoria Jurídica - ASJUR","status":"Aguardando parecer"},{"date":"17/09/2013","unidade_local":"Coordenadoria Legislativa - COOLEG","unidade_destine":"Assessoria de Comissões Permanentes - ASCOPE","status":"Permanência em tramitação"},{"date":"17/09/2013","unidade_local":"Plenário - PLEN","unidade_destine":"Coordenadoria Legislativa - COOLEG","status":"Matéria lida no Expediente"}]}