{"id":"58776","name":"Projeto de Lei nº 9 de 2019","ementa":"Autoriza a concessão de auxílio financeiro para a Associação Amigos Carreteiros de Lomba Grande.","bill_text_link":"https://sapl.camaranh.rs.gov.br/media/sapl/public/materialegislativa/2019/58776/pl-9-2019.pdf","date":"25/02/2019","authors":["Executivo"],"status":[{"date":"08/03/2019","unidade_local":"Secretaria - SECRET","unidade_destine":"Arquivo - ARQUIVO","status":"Lei sancionada pelo(a) chefe do Executivo"},{"date":"08/03/2019","unidade_local":"Poder Executivo Municipal - EXEC","unidade_destine":"Secretaria - SECRET","status":"Lei sancionada pelo(a) chefe do Executivo"},{"date":"27/02/2019","unidade_local":"Secretaria - SECRET","unidade_destine":"Poder Executivo Municipal - EXEC","status":"Autógrafo"},{"date":"27/02/2019","unidade_local":"Plenário - PLEN","unidade_destine":"Secretaria - SECRET","status":"Aprovado(a) em 2ª votação"},{"date":"26/02/2019","unidade_local":"Plenário - PLEN","unidade_destine":"Plenário - PLEN","status":"Aprovado(a) em 1ª votação"},{"date":"25/02/2019","unidade_local":"Plenário - PLEN","unidade_destine":"Plenário - PLEN","status":"Incluído(a) na Ordem do Dia"},{"date":"25/02/2019","unidade_local":"Setor de Apoio Legislativo - APOIO","unidade_destine":"Plenário - PLEN","status":"Aguardando leitura no expediente"}]}