{"id":"10689","name":"Projeto de Lei nº 158 de 2010","ementa":"Desafeta imóveis objeto de cancelamento parcial de loteamento, e dá outras providências.","bill_text_link":"https://sapl.camaranh.rs.gov.br/media/sapl/public/materialegislativa/2010/10689/10689_texto_integral.pdf","date":"09/12/2010","authors":{"0":"Executivo"},"status":{"0":{"date":"20/12/2011","unidade_local":"Plenário - PLEN","unidade_destine":"Arquivo - ARQUIVO","status":"Rejeitado(a) em 2ª votação"},"1":{"date":"19/12/2011","unidade_local":"Plenário - PLEN","unidade_destine":"Plenário - PLEN","status":"Rejeitado em 1ª votação"},"2":{"date":"15/12/2011","unidade_local":"Coordenadoria Legislativa - COOLEG","unidade_destine":"Plenário - PLEN","status":"Incluído(a) na Ordem do Dia"},"3":{"date":"14/02/2011","unidade_local":"Coordenadoria Legislativa - COOLEG","unidade_destine":"Coordenadoria Legislativa - COOLEG","status":"Parecer de constitucionalidade"},"4":{"date":"04/02/2011","unidade_local":"Assessoria Jurídica - ASJUR","unidade_destine":"COJUR - Comissão de Constituição, Justiça e Redação","status":"Aguardando parecer"},"5":{"date":"05/01/2011","unidade_local":"Coordenadoria Legislativa - COOLEG","unidade_destine":"Assessoria Jurídica - ASJUR","status":"Permanência em tramitação"},"6":{"date":"22/12/2010","unidade_local":"Plenário - PLEN","unidade_destine":"Coordenadoria Legislativa - COOLEG","status":"Permanência em tramitação"},"7":{"date":"17/12/2010","unidade_local":"Assessoria Jurídica - ASJUR","unidade_destine":"Plenário - PLEN","status":"Incluído(a) na Ordem do Dia"},"8":{"date":"10/12/2010","unidade_local":"Coordenadoria Legislativa - COOLEG","unidade_destine":"Assessoria Jurídica - ASJUR","status":"Permanência em tramitação"},"9":{"date":"09/12/2010","unidade_local":"Plenário - PLEN","unidade_destine":"Coordenadoria Legislativa - COOLEG","status":"Matéria lida no Expediente"}}}