{"id":"3399","name":"Projeto de Lei nº 210 de 2008","ementa":"Autoriza ao Poder Executivo firmar instrumento de parcelamento de débito relativo ao PASEP, e dá outras providências.","bill_text_link":"https://sapl.camaranh.rs.gov.br/media/sapl/public/materialegislativa/2008/3399/3399_texto_integral.pdf","date":"10/12/2008","authors":{"0":"Executivo"},"status":{"0":{"date":"17/12/2008","unidade_local":"Poder Executivo Municipal - EXEC","unidade_destine":"Arquivo - ARQUIVO","status":"Lei sancionada pelo(a) chefe do Executivo"},"1":{"date":"16/12/2008","unidade_local":"Secretaria - SECRET","unidade_destine":"Poder Executivo Municipal - EXEC","status":"Ofício ao Executivo"},"2":{"date":"15/12/2008","unidade_local":"Plenário - PLEN","unidade_destine":"Secretaria - SECRET","status":"Aprovado(a) em 2ª votação"},"3":{"date":"11/12/2008","unidade_local":"Plenário - PLEN","unidade_destine":"Plenário - PLEN","status":"Aprovado(a) em 1ª votação"},"4":{"date":"11/12/2008","unidade_local":"Plenário - PLEN","unidade_destine":"Plenário - PLEN","status":"Matéria lida no Expediente"}}}