{"id":"41314","name":"Requerimento nº 1202 de 2016","ementa":"Requerem urgência e inclusão do Projeto de Lei nº 88/2016, de autoria do Executivo, que \"altera os dispositivos que menciona na Lei Municipal nº 1.216/2004, que Institui o Plano Diretor Urbanístico Ambiental - PDUA do Município de Novo Hamburgo\", na Ordem do Dia das sessões ordinárias de 17 e 22 de agosto de 2016, para ser apreciado em 1ª e 2ª votações, respectivamente, conforme facultado pelo § 8º do art. 150 do Regimento Interno.","bill_text_link":"https://sapl.camaranh.rs.gov.br/media/sapl/public/materialegislativa/2016/41314/41314_texto_integral.odt","date":"17/08/2016","authors":{"0":"Antonio Lucas","1":"Gerson Peteffi","2":"Naasom Luciano","3":"Roger Corrêa"},"status":{"0":{"date":"12/11/2018","unidade_local":"Arquivo - ARQUIVO","unidade_destine":"Arquivo - ARQUIVO","status":"Processo concluído"},"1":{"date":"17/08/2016","unidade_local":"Plenário - PLEN","unidade_destine":"Arquivo - ARQUIVO","status":"Aprovado(a) em votação única"},"2":{"date":"17/08/2016","unidade_local":"Secretaria - SECRET","unidade_destine":"Plenário - PLEN","status":"Aguardando leitura no expediente"}}}