{"id":"9202","name":"Projeto de Lei nº 78 de 2010","ementa":"Institui a \"Semana de Luta Contra a Intolerância Religiosa\" no calendário oficial de eventos do Município de Novo Hamburgo.","bill_text_link":"https://sapl.camaranh.rs.gov.br/media/sapl/public/materialegislativa/2010/9202/9202_texto_integral.odt","date":"21/07/2010","authors":{"0":"Alexsander Rönnau"},"status":{"0":{"date":"08/12/2010","unidade_local":"Poder Executivo Municipal - EXEC","unidade_destine":"Arquivo - ARQUIVO","status":"Lei sancionada pelo(a) chefe do Executivo"},"1":{"date":"24/11/2010","unidade_local":"Secretaria - SECRET","unidade_destine":"Poder Executivo Municipal - EXEC","status":"Ofício ao Executivo"},"2":{"date":"23/11/2010","unidade_local":"Plenário - PLEN","unidade_destine":"Secretaria - SECRET","status":"Aprovado(a) em votação única"},"3":{"date":"18/11/2010","unidade_local":"Plenário - PLEN","unidade_destine":"Plenário - PLEN","status":"Aprovado(a) em 2ª votação"},"4":{"date":"16/11/2010","unidade_local":"Plenário - PLEN","unidade_destine":"Plenário - PLEN","status":"Aprovado(a) em 1ª votação"},"5":{"date":"11/11/2010","unidade_local":"Mesa Diretora - MD","unidade_destine":"Plenário - PLEN","status":"Incluído(a) na Ordem do Dia"},"6":{"date":"24/08/2010","unidade_local":"COJUR - Comissão de Constituição, Justiça e Redação","unidade_destine":"Mesa Diretora - MD","status":"Parecer de constitucionalidade"},"7":{"date":"09/08/2010","unidade_local":"Assessoria Jurídica - ASJUR","unidade_destine":"COJUR - Comissão de Constituição, Justiça e Redação","status":"Aguardando parecer"},"8":{"date":"22/07/2010","unidade_local":"Plenário - PLEN","unidade_destine":"Assessoria Jurídica - ASJUR","status":"Matéria lida no Expediente"}}}