{"id":"57730","name":"Emenda nº 44 de 2018","ementa":"Suplementa e reduz dotação orçamentária e indica entidades ao Projeto de Lei n. 89/2018","bill_text_link":"https://sapl.camaranh.rs.gov.br/media/sapl/public/materialegislativa/2018/57730/emenda_44-2018_-_luz_loa_2019_Hp6O8ud.odt","date":"27/11/2018","authors":{"0":"Inspetor Luz"},"status":{"0":{"date":"07/12/2018","unidade_local":"Coordenadoria Legislativa - COOLEG","unidade_destine":"Arquivo - ARQUIVO","status":"Processo concluído"},"1":{"date":"05/12/2018","unidade_local":"Plenário - PLEN","unidade_destine":"Coordenadoria Legislativa - COOLEG","status":"Aprovado(a) em 2ª votação"},"2":{"date":"04/12/2018","unidade_local":"Plenário - PLEN","unidade_destine":"Plenário - PLEN","status":"Aprovado(a) em 1ª votação"},"3":{"date":"03/12/2018","unidade_local":"Coordenadoria Legislativa - COOLEG","unidade_destine":"Plenário - PLEN","status":"Incluído(a) na Ordem do Dia"},"4":{"date":"03/12/2018","unidade_local":"Coordenadoria das Comissões - COORDCOM","unidade_destine":"Coordenadoria Legislativa - COOLEG","status":"Permanência em tramitação"},"5":{"date":"27/11/2018","unidade_local":"Setor de Apoio Legislativo - APOIO","unidade_destine":"Coordenadoria das Comissões - COORDCOM","status":"Apresentação de EMENDA"}}}